demo_package_author/__init__.py
demo_package_author/f2c.py
demo_package_author-0.0.1.dist-info/METADATA
demo_package_author-0.0.1.dist-info/WHEEL
demo_package_author-0.0.1.dist-info/entry_points.txt
demo_package_author-0.0.1.dist-info/top_level.txt
demo_package_author-0.0.1.dist-info/RECORD
