Metadata-Version: 2.1
Name: demo-package-author
Version: 0.0.1
Summary: foo is a example project for demo
Author-email: Author <author@demo.com>
Classifier: Programming Language :: Python :: 3
Classifier: License :: OSI Approved :: MIT License
Classifier: Operating System :: OS Independent
Requires-Python: >=3.8
